furiosa/optimizer/__init__.py
furiosa/optimizer/git_version.txt
furiosa/optimizer/py.typed
furiosa/optimizer/frontend/__init__.py
furiosa/optimizer/frontend/onnx/__init__.py
furiosa/optimizer/frontend/onnx/transformer/__init__.py
furiosa/optimizer/frontend/onnx/transformer/convert_negative_pads_to_slice.py
furiosa/optimizer/frontend/onnx/transformer/convert_prelu_to_relu.py
furiosa/optimizer/frontend/onnx/transformer/fuse_batchnorm.py
furiosa/optimizer/frontend/onnx/transformer/fuse_gather_matmul.py
furiosa/optimizer/frontend/onnx/transformer/infer_squeeze_axes.py
furiosa/optimizer/frontend/onnx/transformer/polish_model.py
furiosa/optimizer/frontend/onnx/transformer/utils.py
furiosa/optimizer/frontend/onnx/transformer/experimental/__init__.py
furiosa/optimizer/frontend/onnx/transformer/experimental/eliminate_detection_postprocess.py
furiosa/optimizer/frontend/onnx/transformer/experimental/embedding_bag_porting.py
furiosa/optimizer/frontend/onnx/transformer/experimental/fuse_div_for_bert.py
furiosa/optimizer/frontend/onnx/transformer/experimental/reify_conv_for_bert.py
furiosa/optimizer/frontend/onnx/utils/__init__.py
furiosa/optimizer/frontend/onnx/utils/check_model.py
furiosa/optimizer/frontend/onnx/utils/inference_shape.py
furiosa/optimizer/frontend/onnx/utils/version_checker.py
furiosa/optimizer/interfaces/__init__.py
furiosa/optimizer/interfaces/transformer.py
furiosa_optimizer-0.10.2.dist-info/WHEEL
furiosa_optimizer-0.10.2.dist-info/METADATA
furiosa_optimizer-0.10.2.dist-info/RECORD
